guineajson/__init__.py
guineajson/__main__.py
guineajson-1.1.0.dist-info/licenses/LICENSE
guineajson-1.1.0.dist-info/METADATA
guineajson-1.1.0.dist-info/WHEEL
guineajson-1.1.0.dist-info/top_level.txt
guineajson-1.1.0.dist-info/RECORD
