Metadata-Version: 2.4
Name: GuineaJSON
Version: 1.1.0
Summary: GuineaJSON is a Python module built for handling conversion between JSON arrays/objects to Pythons lists/dictionaries.
Author-email: Dominik Salawa <dominik-salawa-github@outlook.com>
License-Expression: MIT
Project-URL: Homepage, https://github.com/Dominik-Salawa/GuineaJSON
Project-URL: Issues, https://github.com/Dominik-Salawa/GuineaJSON/issues
Classifier: Development Status :: 5 - Production/Stable
Classifier: Operating System :: Microsoft
Classifier: Programming Language :: Python
Classifier: Topic :: File Formats :: JSON
Requires-Python: >=3.6
License-File: LICENSE
Dynamic: license-file
